LICENSE
MANIFEST.in
README.rst
setup.py
gears_uglifyjs/__init__.py
gears_uglifyjs/compressor.js
gears_uglifyjs/compressor.py
gears_uglifyjs.egg-info/PKG-INFO
gears_uglifyjs.egg-info/SOURCES.txt
gears_uglifyjs.egg-info/dependency_links.txt
gears_uglifyjs.egg-info/top_level.txt
gears_uglifyjs/node_modules/uglify-js/.npmignore
gears_uglifyjs/node_modules/uglify-js/README.html
gears_uglifyjs/node_modules/uglify-js/README.org
gears_uglifyjs/node_modules/uglify-js/docstyle.css
gears_uglifyjs/node_modules/uglify-js/package.json
gears_uglifyjs/node_modules/uglify-js/uglify-js.js
gears_uglifyjs/node_modules/uglify-js/bin/uglifyjs
gears_uglifyjs/node_modules/uglify-js/lib/consolidator.js
gears_uglifyjs/node_modules/uglify-js/lib/parse-js.js
gears_uglifyjs/node_modules/uglify-js/lib/process.js
gears_uglifyjs/node_modules/uglify-js/lib/squeeze-more.js
gears_uglifyjs/node_modules/uglify-js/test/beautify.js
gears_uglifyjs/node_modules/uglify-js/test/testconsolidator.js
gears_uglifyjs/node_modules/uglify-js/test/testparser.js
gears_uglifyjs/node_modules/uglify-js/test/unit/scripts.js
gears_uglifyjs/node_modules/uglify-js/test/unit/compress/expected/1e21.js
gears_uglifyjs/node_modules/uglify-js/test/unit/compress/expected/array1.js
gears_uglifyjs/node_modules/uglify-js/test/unit/compress/expected/array2.js
gears_uglifyjs/node_modules/uglify-js/test/unit/compress/expected/array3.js
gears_uglifyjs/node_modules/uglify-js/test/unit/compress/expected/array4.js
gears_uglifyjs/node_modules/uglify-js/test/unit/compress/expected/assignment.js
gears_uglifyjs/node_modules/uglify-js/test/unit/compress/expected/concatstring.js
gears_uglifyjs/node_modules/uglify-js/test/unit/compress/expected/const.js
gears_uglifyjs/node_modules/uglify-js/test/unit/compress/expected/empty-blocks.js
gears_uglifyjs/node_modules/uglify-js/test/unit/compress/expected/forstatement.js
gears_uglifyjs/node_modules/uglify-js/test/unit/compress/expected/if-not.js
gears_uglifyjs/node_modules/uglify-js/test/unit/compress/expected/if.js
gears_uglifyjs/node_modules/uglify-js/test/unit/compress/expected/ifreturn.js
